xiaowupkg/UIfunc.py
xiaowupkg/__init__.py
xiaowupkg/filefunc.py
xiaowupkg-1.0.5.dist-info/METADATA
xiaowupkg-1.0.5.dist-info/WHEEL
xiaowupkg-1.0.5.dist-info/top_level.txt
xiaowupkg-1.0.5.dist-info/RECORD
